pangea_boto3/__init__.py
pangea_boto3/errors.py
pangea_boto3/py.typed
pangea_boto3-0.1.0.dist-info/WHEEL
pangea_boto3-0.1.0.dist-info/METADATA
pangea_boto3-0.1.0.dist-info/RECORD
