Metadata-Version: 2.4
Name: pangea-boto3
Version: 0.1.0
Summary: A wrapper around the boto3 Bedrock Runtime client
Author: Pangea
Author-email: Pangea <support@pangea.cloud>
License-Expression: Apache-2.0
Requires-Dist: boto3>=1.40.27
Requires-Dist: pangea-sdk>=6.6.0
Requires-Dist: typing-extensions>=4.15.0
Requires-Python: >=3.10
